simple_import/__init__.py
simple_import/admin.py
simple_import/forms.py
simple_import/models.py
simple_import/odsreader.py
simple_import/tests.py
simple_import/urls.py
simple_import/utils.py
simple_import/views.py
simple_import/migrations/0001_initial.py
simple_import/migrations/__init__.py
simple_import/templates/simple_import/base.html
simple_import/templates/simple_import/do_import.html
simple_import/templates/simple_import/import.html
simple_import/templates/simple_import/match_columns.html
simple_import/templates/simple_import/match_relations.html
django_simple_import-2.1.0.dist-info/LICENSE
django_simple_import-2.1.0.dist-info/METADATA
django_simple_import-2.1.0.dist-info/WHEEL
django_simple_import-2.1.0.dist-info/top_level.txt
django_simple_import-2.1.0.dist-info/RECORD
